odh_core-0.1.29.dist-info/METADATA
odh_core-0.1.29.dist-info/WHEEL
odh_core/__init__.py
odh_core/akv.py
odh_core/emailclient.py
odh_core/graphql_client.py
odh_core/logger.py
odh_core/logging_settings.py
odh_core/ms_odata.py
odh_core/phonenumber.py
odh_core/ssn.py
odh_core/twilio.py
odh_core-0.1.29.dist-info/RECORD
