Metadata-Version: 2.1
Name: odh-core
Version: 0.1.29
Summary: ODH Core, helper functions and classes
Author-Email: Jimmy Spets <jimmy.spets@waochurch.com>, Viktor Freiman <viktor.freiman@waochurch.com>
License: MIT
Requires-Python: >=3.10
Requires-Dist: gql[aiohttp]
Requires-Dist: personnummer
Requires-Dist: phonenumbers
Requires-Dist: python-dotenv
Requires-Dist: python-jose[cryptography]
Requires-Dist: azure-identity; extra == "dev"
Requires-Dist: azure-keyvault-secrets; extra == "dev"
Requires-Dist: black; extra == "dev"
Requires-Dist: docs-helper; extra == "dev"
Requires-Dist: pytest-asyncio; extra == "dev"
Requires-Dist: pytest; extra == "dev"
Requires-Dist: rinohtype; extra == "dev"
Requires-Dist: ruff; extra == "dev"
Requires-Dist: sphinx-autobuild; extra == "dev"
Requires-Dist: sphinx-rtd-theme; extra == "dev"
Requires-Dist: Sphinx; extra == "dev"
Requires-Dist: sphinxcontrib-autoprogram; extra == "dev"
Requires-Dist: toml; extra == "dev"
Provides-Extra: dev
